[ {
  "id" : "cc8c95de-1980-3c09-d340-85a469f03b50",
  "name" : "intro_to_title",
  "label" : "Intro To Title",
  "required" : false,
  "locked" : false,
  "allow_new_line" : false,
  "show_emoji_picker" : true,
  "type" : "text",
  "display_width" : null,
  "default" : "Intro Title"
}, {
  "id" : "cd3717f4-102c-4d17-2bca-fb6bf0a1ce92",
  "name" : "title",
  "label" : "Title",
  "required" : false,
  "locked" : false,
  "allow_new_line" : false,
  "show_emoji_picker" : true,
  "type" : "text",
  "display_width" : null,
  "default" : "SECTION FORM - TITLE"
}, {
  "id" : "b05162a4-bcf6-2304-315a-6cd25e0b8dd9",
  "name" : "title_sel_heading",
  "label" : "Title - Header Type",
  "required" : false,
  "locked" : false,
  "visibility" : {
    "controlling_field" : "cd3717f4-102c-4d17-2bca-fb6bf0a1ce92",
    "controlling_field_path" : null,
    "controlling_value_regex" : null,
    "property" : null,
    "operator" : "NOT_EMPTY",
    "access" : null
  },
  "display" : "select",
  "choices" : [ [ "h1", "H1" ], [ "h2", "H2" ], [ "h3", "H3" ], [ "h4", "H4" ] ],
  "multiple" : false,
  "reordering_enabled" : true,
  "preset" : null,
  "type" : "choice",
  "display_width" : null,
  "default" : "h2"
}, {
  "id" : "92f0e3aa-f082-9100-f350-c29af4bcfeda",
  "name" : "description",
  "label" : "Description",
  "required" : false,
  "locked" : false,
  "type" : "richtext",
  "display_width" : null,
  "default" : "<span>Description. Lorem ipsum dolor sit amet, consetetur sadipscing elitr, sed diam nonumy eirmod tempor invidunt ut labore et</span>"
}, {
  "id" : "c9c5d1dd-024c-37d0-95d7-aeb0053390e5",
  "name" : "form",
  "label" : "Form",
  "required" : false,
  "locked" : false,
  "type" : "form",
  "display_width" : null,
  "default" : {
    "response_type" : "inline",
    "message" : "Thanks for submitting the form."
  }
}, {
  "id" : "ac6ae318-dee4-1ee0-987b-40fd14a9778c",
  "name" : "use_followup_email",
  "label" : "Send a follow-up email",
  "required" : false,
  "locked" : false,
  "display" : "checkbox",
  "type" : "boolean",
  "display_width" : null,
  "default" : false
}, {
  "id" : "b01916e7-94d8-923c-f710-33907e613316",
  "name" : "followup_email",
  "label" : "Follow-up email",
  "required" : false,
  "locked" : false,
  "visibility" : {
    "controlling_field" : "ac6ae318-dee4-1ee0-987b-40fd14a9778c",
    "controlling_field_path" : null,
    "controlling_value_regex" : "true",
    "property" : null,
    "operator" : "EQUAL",
    "access" : null
  },
  "type" : "followupemail",
  "display_width" : null
}, {
  "id" : "9f44d539-7e44-b29d-f473-fd5fd625600b",
  "name" : "layout",
  "label" : "Layout",
  "required" : false,
  "locked" : false,
  "children" : [ {
    "id" : "a44de396-9ae2-c2af-6627-a4948cd9def4",
    "name" : "section_variant",
    "label" : "Choose Layout",
    "help_text" : "",
    "required" : true,
    "locked" : false,
    "display" : "select",
    "choices" : [ [ "hor_55", "Horizontal (50/50)" ], [ "hor_64", "Horizontal (60/40)" ], [ "hor_boxed", "Horizontal Boxed" ], [ "vert", "Vertical (wide)" ], [ "vert_narrow", "Vertical (narrow)" ] ],
    "multiple" : false,
    "reordering_enabled" : true,
    "preset" : null,
    "type" : "choice",
    "display_width" : null,
    "default" : "vert"
  }, {
    "id" : "1cf87f33-64ed-11fb-69f1-cf98fd7e2fac",
    "name" : "centered",
    "label" : "Centered",
    "help_text" : "Only for vertical layout",
    "required" : false,
    "locked" : false,
    "display" : "checkbox",
    "type" : "boolean",
    "display_width" : null,
    "default" : false
  }, {
    "id" : "c6e084a3-7d44-deee-6966-6b32a065c78d",
    "name" : "padding_top",
    "label" : "Padding Top",
    "required" : true,
    "locked" : false,
    "display" : "select",
    "choices" : [ [ " ", "Standard" ], [ "pwr--padding-t-0", "None" ], [ "pwr--sec-padding-t-sm", "Small" ], [ "pwr--sec-padding-t-md", "Medium" ], [ "pwr--sec-padding-t-lg", "Large" ], [ "pwr-sec--first-with-header", "First Section With Header" ] ],
    "multiple" : false,
    "reordering_enabled" : true,
    "preset" : null,
    "type" : "choice",
    "display_width" : null,
    "default" : " "
  }, {
    "id" : "2aa8eb22-e63e-e28a-737b-c5ee954b2fa2",
    "name" : "padding_bottom",
    "label" : "Padding Bottom",
    "required" : true,
    "locked" : false,
    "display" : "select",
    "choices" : [ [ " ", "Standard" ], [ "pwr--padding-b-0", "None" ], [ "pwr--sec-padding-b-sm", "Small" ], [ "pwr--sec-padding-b-md", "Medium" ], [ "pwr--sec-padding-b-lg", "Large" ] ],
    "multiple" : false,
    "reordering_enabled" : true,
    "preset" : null,
    "type" : "choice",
    "display_width" : null,
    "default" : " "
  } ],
  "tab" : "CONTENT",
  "expanded" : false,
  "group_occurrence_meta" : null,
  "type" : "group",
  "display_width" : null,
  "default" : {
    "section_variant" : "vert",
    "centered" : false,
    "padding_top" : " ",
    "padding_bottom" : " "
  }
}, {
  "id" : "231266df-0a2f-9b1c-b375-6b27e397d21c",
  "name" : "style",
  "label" : "Style",
  "required" : false,
  "locked" : false,
  "children" : [ {
    "id" : "a1baa8f2-a43c-9d57-f432-3ea87840a2fe",
    "name" : "scheme",
    "label" : "Color Scheme",
    "help_text" : "Predefined light or dark color scheme. \nLight -> Light background and dark font color.\nDark -> Dark background and light font color.\nNote: You can optionally overwrite the background with further settings",
    "required" : false,
    "locked" : false,
    "display" : "radio",
    "choices" : [ [ "light", "Light" ], [ "dark", "Dark" ] ],
    "multiple" : false,
    "reordering_enabled" : true,
    "preset" : null,
    "type" : "choice",
    "display_width" : null,
    "default" : "light"
  }, {
    "id" : "a921d915-588a-b443-4c1a-49122fbf0bca",
    "name" : "btn_style",
    "label" : "Button Style",
    "required" : false,
    "locked" : false,
    "display" : "select",
    "choices" : [ [ "pwr-btn--primary-solid", "Solid Primary" ], [ "pwr-btn--regular-solid", "Solid Regular" ], [ "pwr-btn--regular-solid-primary-background", "Solid Regular For Primary Background" ], [ "pwr-btn--primary-border", "Border Primary" ], [ "pwr-btn--regular-border", "Border Regular" ] ],
    "multiple" : false,
    "reordering_enabled" : true,
    "preset" : null,
    "type" : "choice",
    "display_width" : null,
    "default" : "pwr-btn--primary-solid"
  }, {
    "id" : "6504194e-3b11-8a5e-4b0b-bb935d73ddc9",
    "name" : "overwrite_box_color",
    "label" : "Overwrite Box Color",
    "help_text" : "Only for layout \"Horizontal Boxed\"",
    "required" : false,
    "locked" : false,
    "display" : "checkbox",
    "type" : "boolean",
    "display_width" : null,
    "default" : false
  }, {
    "id" : "10d42eb8-6a16-bbc1-2647-fb1562f023df",
    "name" : "box_scheme",
    "label" : "Box Color Scheme",
    "help_text" : "Predefined light or dark color scheme. \nLight -> Light background and dark font color.\nDark -> Dark background and light font color.\nNote: You can optionally overwrite the background with further settings",
    "required" : false,
    "locked" : false,
    "visibility" : {
      "controlling_field" : "6504194e-3b11-8a5e-4b0b-bb935d73ddc9",
      "controlling_field_path" : null,
      "controlling_value_regex" : "true",
      "property" : null,
      "operator" : "EQUAL",
      "access" : null
    },
    "display" : "radio",
    "choices" : [ [ "light", "Light" ], [ "dark", "Dark" ] ],
    "multiple" : false,
    "reordering_enabled" : true,
    "preset" : null,
    "type" : "choice",
    "display_width" : null,
    "default" : "light"
  }, {
    "id" : "a595b3ac-8b46-3f79-49a2-bf80a34e6620",
    "name" : "box_color",
    "label" : "Custom Box Background Color ",
    "required" : false,
    "locked" : false,
    "visibility" : {
      "controlling_field" : "6504194e-3b11-8a5e-4b0b-bb935d73ddc9",
      "controlling_field_path" : null,
      "controlling_value_regex" : "true",
      "property" : null,
      "operator" : "EQUAL",
      "access" : null
    },
    "type" : "color",
    "display_width" : null,
    "default" : {
      "color" : null,
      "opacity" : 100
    }
  }, {
    "id" : "31eebccd-7a5b-a980-3af5-472ae598e9d8",
    "name" : "background",
    "label" : "Background",
    "help_text" : "Optionally overwrite the default background with a custom background-color, a background-image / -video or a gradient",
    "required" : false,
    "locked" : false,
    "display" : "select",
    "choices" : [ [ "color", "Background Color" ], [ "img_vid", "Background Image / Video" ], [ "gradient", "Background Gradient" ] ],
    "multiple" : false,
    "reordering_enabled" : true,
    "preset" : null,
    "type" : "choice",
    "display_width" : null,
    "default" : ""
  }, {
    "id" : "1fc03c0b-792b-04d6-fd94-9245acc6ee7f",
    "name" : "background_color",
    "label" : "Background Color",
    "required" : false,
    "locked" : false,
    "visibility" : {
      "controlling_field" : "31eebccd-7a5b-a980-3af5-472ae598e9d8",
      "controlling_field_path" : null,
      "controlling_value_regex" : "color",
      "property" : null,
      "operator" : "EQUAL",
      "access" : null
    },
    "type" : "color",
    "display_width" : null,
    "default" : {
      "color" : "#F4F6FA",
      "opacity" : 100
    }
  }, {
    "id" : "df6d581d-b1f2-8a9d-a318-1efce42ee696",
    "name" : "background_image",
    "label" : "Background Image / Placeholder Image (Video)",
    "help_text" : "The image should be at least 2000 pixels in width",
    "required" : false,
    "locked" : false,
    "visibility" : {
      "controlling_field" : "31eebccd-7a5b-a980-3af5-472ae598e9d8",
      "controlling_field_path" : null,
      "controlling_value_regex" : "img_vid",
      "property" : null,
      "operator" : "EQUAL",
      "access" : null
    },
    "responsive" : false,
    "resizable" : false,
    "show_loading" : false,
    "type" : "image",
    "display_width" : null,
    "default" : {
      "src" : "",
      "alt" : null
    }
  }, {
    "picker" : "file",
    "id" : "54c4aca2-5a51-54e0-929e-60d37ae14492",
    "name" : "background_video",
    "label" : "Background Video - *.mp4",
    "help_text" : "If a custom video (*.mp4) is configured here, it will overwrite the background image.\nPlease make sure that the file size is not too big. A general rule of thumb is to keep reducing the file size until it starts to noticeably be degraded. Try to export videos in 720p and with a bitrate under 700kb/s ( preferably 500kb/s ).",
    "required" : false,
    "locked" : false,
    "visibility" : {
      "controlling_field" : "31eebccd-7a5b-a980-3af5-472ae598e9d8",
      "controlling_field_path" : null,
      "controlling_value_regex" : "img_vid",
      "property" : null,
      "operator" : "EQUAL",
      "access" : null
    },
    "type" : "file",
    "display_width" : null
  }, {
    "id" : "121abe22-f878-ad15-2edf-533c3c21016c",
    "name" : "youtube_link",
    "label" : "Background Video - Youtube",
    "help_text" : "Enter your Youtube Link or ID. This will overwrite the previously configured background image or custom background video *.mp4",
    "required" : false,
    "locked" : false,
    "visibility" : {
      "controlling_field" : "31eebccd-7a5b-a980-3af5-472ae598e9d8",
      "controlling_field_path" : null,
      "controlling_value_regex" : "img_vid",
      "property" : null,
      "operator" : "EQUAL",
      "access" : null
    },
    "allow_new_line" : false,
    "type" : "text",
    "display_width" : null
  }, {
    "id" : "bce7b890-f3a5-ef21-29c5-9cc6d4a9f795",
    "name" : "background_position",
    "label" : "Background Position / Parallax Effect",
    "required" : false,
    "locked" : false,
    "visibility" : {
      "controlling_field" : "31eebccd-7a5b-a980-3af5-472ae598e9d8",
      "controlling_field_path" : null,
      "controlling_value_regex" : "img_vid",
      "property" : null,
      "operator" : "EQUAL",
      "access" : null
    },
    "display" : "select",
    "choices" : [ [ "bottom", "Bottom" ], [ "center", "Center" ], [ "left", "Left" ], [ "right", "Right" ], [ "top", "Top" ], [ "parallax", "Parallax" ] ],
    "multiple" : false,
    "reordering_enabled" : true,
    "preset" : null,
    "type" : "choice",
    "display_width" : null,
    "default" : "center"
  }, {
    "id" : "35e07bf0-8869-84d6-bfb0-f9be2010807a",
    "name" : "background_image_overlay",
    "label" : "Background Image Overlay",
    "required" : false,
    "locked" : false,
    "visibility" : {
      "controlling_field" : "31eebccd-7a5b-a980-3af5-472ae598e9d8",
      "controlling_field_path" : null,
      "controlling_value_regex" : "img_vid",
      "property" : null,
      "operator" : "EQUAL",
      "access" : null
    },
    "display" : "radio",
    "choices" : [ [ "color", "Color" ], [ "gradient", "Gradient" ] ],
    "multiple" : false,
    "reordering_enabled" : true,
    "preset" : null,
    "type" : "choice",
    "display_width" : null,
    "default" : "color"
  }, {
    "id" : "e0b2e916-9c5a-fe86-d116-9aa9aab50c18",
    "name" : "overlay_color",
    "label" : "Overlay Color",
    "help_text" : "Set the opacity to 0% if you do not want to use an overlay",
    "required" : false,
    "locked" : false,
    "visibility" : {
      "controlling_field" : "31eebccd-7a5b-a980-3af5-472ae598e9d8",
      "controlling_field_path" : null,
      "controlling_value_regex" : "img_vid",
      "property" : null,
      "operator" : "EQUAL",
      "access" : null
    },
    "type" : "color",
    "display_width" : null,
    "default" : {
      "color" : "#1a1d17",
      "opacity" : 40
    }
  }, {
    "id" : "793dd27a-344c-fde9-0c5c-d6e247d4f19e",
    "name" : "overlay_gradient_direction",
    "label" : "Overlay Gradient Direction",
    "required" : false,
    "locked" : false,
    "visibility" : {
      "controlling_field" : "31eebccd-7a5b-a980-3af5-472ae598e9d8",
      "controlling_field_path" : null,
      "controlling_value_regex" : "img_vid",
      "property" : null,
      "operator" : "EQUAL",
      "access" : null
    },
    "display" : "select",
    "choices" : [ [ "hor", "Horizontal - Left to Right" ], [ "vert", "Vertical - Top to Bottom" ], [ "diag_tl_br", "Diagonal - Top Left to Right Bottom" ], [ "diag_bl_tr", "Diagonal - Bottom Left to Top Right" ] ],
    "multiple" : false,
    "reordering_enabled" : true,
    "preset" : null,
    "type" : "choice",
    "display_width" : null,
    "default" : "hor"
  }, {
    "id" : "595f9bc9-56f1-cc6f-8869-a1376e7f7995",
    "name" : "overlay_gradient_color_1",
    "label" : "Overlay Gradient Color 1",
    "help_text" : "Opacity setting only works in modern versions of Chrome, Safari and Opera. \nAlternatively you can configure the general opacity for the whole gradient overlay",
    "required" : false,
    "locked" : false,
    "visibility" : {
      "controlling_field" : "31eebccd-7a5b-a980-3af5-472ae598e9d8",
      "controlling_field_path" : null,
      "controlling_value_regex" : "img_vid",
      "property" : null,
      "operator" : "EQUAL",
      "access" : null
    },
    "type" : "color",
    "display_width" : null,
    "default" : {
      "color" : "#ffffff",
      "opacity" : 100
    }
  }, {
    "id" : "d5022779-0958-7717-0787-49dc20c11f75",
    "name" : "overlay_gradient_color_2",
    "label" : "Overlay Gradient Color 2",
    "help_text" : "Opacity setting only works in modern versions of Chrome, Safari and Opera. \nAlternatively you can configure the general opacity for the whole gradient overlay",
    "required" : false,
    "locked" : false,
    "visibility" : {
      "controlling_field" : "31eebccd-7a5b-a980-3af5-472ae598e9d8",
      "controlling_field_path" : null,
      "controlling_value_regex" : "img_vid",
      "property" : null,
      "operator" : "EQUAL",
      "access" : null
    },
    "type" : "color",
    "display_width" : null,
    "default" : {
      "color" : "#ffffff",
      "opacity" : 100
    }
  }, {
    "id" : "91d2a009-ef2d-fbe2-c110-c7eba801de19",
    "name" : "overlay_gradient_opacity",
    "label" : "Overlay Gradient Opacity in %",
    "help_text" : "General opacity for the gradient overlay. Overwrites individual opacity settings of the gradient colors, if not 100% -> General opacity for the gradient overlay. Overwrites individual opacity settings of the gradient colors",
    "required" : false,
    "locked" : false,
    "visibility" : {
      "controlling_field" : "31eebccd-7a5b-a980-3af5-472ae598e9d8",
      "controlling_field_path" : null,
      "controlling_value_regex" : "img_vid",
      "property" : null,
      "operator" : "EQUAL",
      "access" : null
    },
    "display" : "text",
    "min" : 1,
    "max" : 100,
    "step" : 1,
    "type" : "number",
    "display_width" : null,
    "default" : 100
  }, {
    "id" : "ad81404f-40cf-0a02-a76a-45bc72a5272a",
    "name" : "background_gradient_direction",
    "label" : "Background Gradient Direction",
    "required" : false,
    "locked" : false,
    "visibility" : {
      "controlling_field" : "31eebccd-7a5b-a980-3af5-472ae598e9d8",
      "controlling_field_path" : null,
      "controlling_value_regex" : "gradient",
      "property" : null,
      "operator" : "EQUAL",
      "access" : null
    },
    "display" : "select",
    "choices" : [ [ "hor", "Horizontal - Left to Right" ], [ "vert", "Vertical - Top to Bottom" ], [ "diag_tl_br", "Diagonal - Top Left to Right Bottom" ], [ "diag_bl_tr", "Diagonal - Bottom Left to Top Right" ] ],
    "multiple" : false,
    "reordering_enabled" : true,
    "preset" : null,
    "type" : "choice",
    "display_width" : null,
    "default" : "hor"
  }, {
    "id" : "00a049e6-ea9f-9ef1-eda1-570a6b30ed54",
    "name" : "background_gradient_color_1",
    "label" : "Background Gradient Color 1",
    "required" : false,
    "locked" : false,
    "visibility" : {
      "controlling_field" : "31eebccd-7a5b-a980-3af5-472ae598e9d8",
      "controlling_field_path" : null,
      "controlling_value_regex" : "gradient",
      "property" : null,
      "operator" : "EQUAL",
      "access" : null
    },
    "type" : "color",
    "display_width" : null,
    "default" : {
      "color" : "#ffffff",
      "opacity" : 100
    }
  }, {
    "id" : "8bb34386-47ba-da71-4690-592660474606",
    "name" : "background_gradient_color_2",
    "label" : "Background Gradient Color 2",
    "required" : false,
    "locked" : false,
    "visibility" : {
      "controlling_field" : "31eebccd-7a5b-a980-3af5-472ae598e9d8",
      "controlling_field_path" : null,
      "controlling_value_regex" : "gradient",
      "property" : null,
      "operator" : "EQUAL",
      "access" : null
    },
    "type" : "color",
    "display_width" : null,
    "default" : {
      "color" : "#ffffff",
      "opacity" : 100
    }
  } ],
  "tab" : "CONTENT",
  "expanded" : false,
  "group_occurrence_meta" : null,
  "type" : "group",
  "display_width" : null,
  "default" : {
    "scheme" : "light",
    "btn_style" : "pwr-btn--primary-solid",
    "overwrite_box_color" : false,
    "box_scheme" : "light",
    "box_color" : {
      "color" : null,
      "opacity" : 100
    },
    "background" : "",
    "background_color" : {
      "color" : "#F4F6FA",
      "opacity" : 100
    },
    "background_image" : {
      "src" : "",
      "alt" : null
    },
    "background_position" : "center",
    "background_image_overlay" : "color",
    "overlay_color" : {
      "color" : "#1a1d17",
      "opacity" : 40
    },
    "overlay_gradient_direction" : "hor",
    "overlay_gradient_color_1" : {
      "color" : "#ffffff",
      "opacity" : 100
    },
    "overlay_gradient_color_2" : {
      "color" : "#ffffff",
      "opacity" : 100
    },
    "overlay_gradient_opacity" : 100,
    "background_gradient_direction" : "hor",
    "background_gradient_color_1" : {
      "color" : "#ffffff",
      "opacity" : 100
    },
    "background_gradient_color_2" : {
      "color" : "#ffffff",
      "opacity" : 100
    }
  }
}, {
  "id" : "animation",
  "name" : "animation",
  "label" : "Animation",
  "inline_help_text" : "Please open preview in a new tab/window to preview the animations.",
  "required" : false,
  "locked" : false,
  "children" : [ {
    "id" : "is_aos",
    "name" : "is_aos",
    "label" : "Animate on Scroll?",
    "help_text" : "Turn on/off animation on scroll for this module.",
    "required" : false,
    "locked" : false,
    "display" : "checkbox",
    "type" : "boolean",
    "display_width" : null,
    "default" : true
  }, {
    "id" : "animation.section",
    "name" : "section",
    "label" : "Section",
    "required" : false,
    "locked" : false,
    "children" : [ {
      "id" : "animation.section.animation_type",
      "name" : "animation_type",
      "label" : "Animation Type",
      "required" : true,
      "locked" : false,
      "visibility" : {
        "controlling_field" : "is_aos",
        "controlling_field_path" : null,
        "controlling_value_regex" : "true",
        "property" : null,
        "operator" : "EQUAL",
        "access" : null
      },
      "display" : "select",
      "choices" : [ [ "none", "None" ], [ "default", "Default" ], [ "fade-in", "Fade" ], [ "fade-up", "Fade Up" ], [ "fade-down", "Fade Down" ], [ "fade-left", "Fade Left" ], [ "fade-right", "Fade Right" ], [ "fade-up-right", "Fade Up Right" ], [ "fade-up-left", "Fade Up Left" ], [ "fade-down-right", "Fade Down Right" ], [ "fade-down-left", "Fade Down Left" ], [ "flip-up", "Flip Up" ], [ "flip-down", "Flip Down" ], [ "flip-left", "Flip Left" ], [ "flip-right", "Flip Right" ], [ "slide-up", "Slide Up" ], [ "slide-down", "Slide Down" ], [ "slide-left", "Slide Left" ], [ "slide-right", "Slide Right" ], [ "zoom-in", "Zoom In" ], [ "zoom-in-up", "Zoom In Up " ], [ "zoom-in-down", "Zoom In Down" ], [ "zoom-in-left", "Zoom In Left" ], [ "zoom-in-right", "Zoom In Right" ], [ "zoom-out", "Zoom Out" ], [ "zoom-out-up", "Zoom Out Up" ], [ "zoom-out-down", "Zoom Out Down" ], [ "zoom-out-left", "Zoom Out Left" ], [ "zoom-out-right", "Zoom Out Right" ] ],
      "multiple" : false,
      "reordering_enabled" : true,
      "preset" : null,
      "type" : "choice",
      "display_width" : null,
      "default" : "none"
    }, {
      "id" : "animation.section.delay",
      "name" : "delay",
      "label" : "Delay",
      "help_text" : "Values from 0 to 3000, with step 50ms",
      "inline_help_text" : "Leave blank for default value from theme settings.",
      "required" : false,
      "locked" : false,
      "visibility" : {
        "controlling_field" : "is_aos",
        "controlling_field_path" : null,
        "controlling_value_regex" : "true",
        "property" : null,
        "operator" : "EQUAL",
        "access" : null
      },
      "display" : "text",
      "min" : 0,
      "max" : 3000,
      "step" : 50,
      "type" : "number",
      "display_width" : null
    } ],
    "tab" : "CONTENT",
    "expanded" : false,
    "group_occurrence_meta" : null,
    "type" : "group",
    "display_width" : null
  }, {
    "id" : "animation.intro_to_title",
    "name" : "intro_to_title",
    "label" : "Intro to Title",
    "required" : false,
    "locked" : false,
    "children" : [ {
      "id" : "animation.intro_to_title.animation_type",
      "name" : "animation_type",
      "label" : "Animation Type",
      "required" : true,
      "locked" : false,
      "visibility" : {
        "controlling_field" : "is_aos",
        "controlling_field_path" : null,
        "controlling_value_regex" : "true",
        "property" : null,
        "operator" : "EQUAL",
        "access" : null
      },
      "display" : "select",
      "choices" : [ [ "none", "None" ], [ "default", "Default" ], [ "fade-in", "Fade" ], [ "fade-up", "Fade Up" ], [ "fade-down", "Fade Down" ], [ "fade-left", "Fade Left" ], [ "fade-right", "Fade Right" ], [ "fade-up-right", "Fade Up Right" ], [ "fade-up-left", "Fade Up Left" ], [ "fade-down-right", "Fade Down Right" ], [ "fade-down-left", "Fade Down Left" ], [ "flip-up", "Flip Up" ], [ "flip-down", "Flip Down" ], [ "flip-left", "Flip Left" ], [ "flip-right", "Flip Right" ], [ "slide-up", "Slide Up" ], [ "slide-down", "Slide Down" ], [ "slide-left", "Slide Left" ], [ "slide-right", "Slide Right" ], [ "zoom-in", "Zoom In" ], [ "zoom-in-up", "Zoom In Up " ], [ "zoom-in-down", "Zoom In Down" ], [ "zoom-in-left", "Zoom In Left" ], [ "zoom-in-right", "Zoom In Right" ], [ "zoom-out", "Zoom Out" ], [ "zoom-out-up", "Zoom Out Up" ], [ "zoom-out-down", "Zoom Out Down" ], [ "zoom-out-left", "Zoom Out Left" ], [ "zoom-out-right", "Zoom Out Right" ] ],
      "multiple" : false,
      "reordering_enabled" : true,
      "preset" : null,
      "type" : "choice",
      "display_width" : null,
      "default" : "default"
    }, {
      "id" : "animation.intro_to_title.delay",
      "name" : "delay",
      "label" : "Delay",
      "help_text" : "Values from 0 to 3000, with step 50ms",
      "inline_help_text" : "Leave blank for default value from theme settings.",
      "required" : false,
      "locked" : false,
      "visibility" : {
        "controlling_field" : "is_aos",
        "controlling_field_path" : null,
        "controlling_value_regex" : "true",
        "property" : null,
        "operator" : "EQUAL",
        "access" : null
      },
      "display" : "text",
      "min" : 0,
      "max" : 3000,
      "step" : 50,
      "type" : "number",
      "display_width" : null
    } ],
    "tab" : "CONTENT",
    "expanded" : false,
    "group_occurrence_meta" : null,
    "type" : "group",
    "display_width" : null
  }, {
    "id" : "animation.title",
    "name" : "title",
    "label" : "Title",
    "required" : false,
    "locked" : false,
    "children" : [ {
      "id" : "animation.title.animation_type",
      "name" : "animation_type",
      "label" : "Animation Type",
      "required" : true,
      "locked" : false,
      "visibility" : {
        "controlling_field" : "is_aos",
        "controlling_field_path" : null,
        "controlling_value_regex" : "true",
        "property" : null,
        "operator" : "EQUAL",
        "access" : null
      },
      "display" : "select",
      "choices" : [ [ "none", "None" ], [ "default", "Default" ], [ "fade-in", "Fade" ], [ "fade-up", "Fade Up" ], [ "fade-down", "Fade Down" ], [ "fade-left", "Fade Left" ], [ "fade-right", "Fade Right" ], [ "fade-up-right", "Fade Up Right" ], [ "fade-up-left", "Fade Up Left" ], [ "fade-down-right", "Fade Down Right" ], [ "fade-down-left", "Fade Down Left" ], [ "flip-up", "Flip Up" ], [ "flip-down", "Flip Down" ], [ "flip-left", "Flip Left" ], [ "flip-right", "Flip Right" ], [ "slide-up", "Slide Up" ], [ "slide-down", "Slide Down" ], [ "slide-left", "Slide Left" ], [ "slide-right", "Slide Right" ], [ "zoom-in", "Zoom In" ], [ "zoom-in-up", "Zoom In Up " ], [ "zoom-in-down", "Zoom In Down" ], [ "zoom-in-left", "Zoom In Left" ], [ "zoom-in-right", "Zoom In Right" ], [ "zoom-out", "Zoom Out" ], [ "zoom-out-up", "Zoom Out Up" ], [ "zoom-out-down", "Zoom Out Down" ], [ "zoom-out-left", "Zoom Out Left" ], [ "zoom-out-right", "Zoom Out Right" ] ],
      "multiple" : false,
      "reordering_enabled" : true,
      "preset" : null,
      "type" : "choice",
      "display_width" : null,
      "default" : "default"
    }, {
      "id" : "animation.title.delay",
      "name" : "delay",
      "label" : "Delay",
      "help_text" : "Values from 0 to 3000, with step 50ms",
      "inline_help_text" : "Leave blank for default value from theme settings.",
      "required" : false,
      "locked" : false,
      "visibility" : {
        "controlling_field" : "is_aos",
        "controlling_field_path" : null,
        "controlling_value_regex" : "true",
        "property" : null,
        "operator" : "EQUAL",
        "access" : null
      },
      "display" : "text",
      "min" : 0,
      "max" : 3000,
      "step" : 50,
      "type" : "number",
      "display_width" : null
    } ],
    "tab" : "CONTENT",
    "expanded" : false,
    "group_occurrence_meta" : null,
    "type" : "group",
    "display_width" : null
  }, {
    "id" : "animation.description",
    "name" : "description",
    "label" : "Description",
    "required" : false,
    "locked" : false,
    "children" : [ {
      "id" : "animation.description.animation_type",
      "name" : "animation_type",
      "label" : "Animation Type",
      "required" : true,
      "locked" : false,
      "visibility" : {
        "controlling_field" : "is_aos",
        "controlling_field_path" : null,
        "controlling_value_regex" : "true",
        "property" : null,
        "operator" : "EQUAL",
        "access" : null
      },
      "display" : "select",
      "choices" : [ [ "none", "None" ], [ "default", "Default" ], [ "fade-in", "Fade" ], [ "fade-up", "Fade Up" ], [ "fade-down", "Fade Down" ], [ "fade-left", "Fade Left" ], [ "fade-right", "Fade Right" ], [ "fade-up-right", "Fade Up Right" ], [ "fade-up-left", "Fade Up Left" ], [ "fade-down-right", "Fade Down Right" ], [ "fade-down-left", "Fade Down Left" ], [ "flip-up", "Flip Up" ], [ "flip-down", "Flip Down" ], [ "flip-left", "Flip Left" ], [ "flip-right", "Flip Right" ], [ "slide-up", "Slide Up" ], [ "slide-down", "Slide Down" ], [ "slide-left", "Slide Left" ], [ "slide-right", "Slide Right" ], [ "zoom-in", "Zoom In" ], [ "zoom-in-up", "Zoom In Up " ], [ "zoom-in-down", "Zoom In Down" ], [ "zoom-in-left", "Zoom In Left" ], [ "zoom-in-right", "Zoom In Right" ], [ "zoom-out", "Zoom Out" ], [ "zoom-out-up", "Zoom Out Up" ], [ "zoom-out-down", "Zoom Out Down" ], [ "zoom-out-left", "Zoom Out Left" ], [ "zoom-out-right", "Zoom Out Right" ] ],
      "multiple" : false,
      "reordering_enabled" : true,
      "preset" : null,
      "type" : "choice",
      "display_width" : null,
      "default" : "default"
    }, {
      "id" : "animation.description.delay",
      "name" : "delay",
      "label" : "Delay",
      "help_text" : "Values from 0 to 3000, with step 50ms",
      "inline_help_text" : "Leave blank for default value from theme settings.",
      "required" : false,
      "locked" : false,
      "visibility" : {
        "controlling_field" : "is_aos",
        "controlling_field_path" : null,
        "controlling_value_regex" : "true",
        "property" : null,
        "operator" : "EQUAL",
        "access" : null
      },
      "display" : "text",
      "min" : 0,
      "max" : 3000,
      "step" : 50,
      "type" : "number",
      "display_width" : null
    } ],
    "tab" : "CONTENT",
    "expanded" : false,
    "group_occurrence_meta" : null,
    "type" : "group",
    "display_width" : null
  }, {
    "id" : "animation.form",
    "name" : "form",
    "label" : "Form",
    "required" : false,
    "locked" : false,
    "children" : [ {
      "id" : "animation.form.animation_type",
      "name" : "animation_type",
      "label" : "Animation Type",
      "required" : true,
      "locked" : false,
      "visibility" : {
        "controlling_field" : "is_aos",
        "controlling_field_path" : null,
        "controlling_value_regex" : "true",
        "property" : null,
        "operator" : "EQUAL",
        "access" : null
      },
      "display" : "select",
      "choices" : [ [ "none", "None" ], [ "default", "Default" ], [ "fade-in", "Fade" ], [ "fade-up", "Fade Up" ], [ "fade-down", "Fade Down" ], [ "fade-left", "Fade Left" ], [ "fade-right", "Fade Right" ], [ "fade-up-right", "Fade Up Right" ], [ "fade-up-left", "Fade Up Left" ], [ "fade-down-right", "Fade Down Right" ], [ "fade-down-left", "Fade Down Left" ], [ "flip-up", "Flip Up" ], [ "flip-down", "Flip Down" ], [ "flip-left", "Flip Left" ], [ "flip-right", "Flip Right" ], [ "slide-up", "Slide Up" ], [ "slide-down", "Slide Down" ], [ "slide-left", "Slide Left" ], [ "slide-right", "Slide Right" ], [ "zoom-in", "Zoom In" ], [ "zoom-in-up", "Zoom In Up " ], [ "zoom-in-down", "Zoom In Down" ], [ "zoom-in-left", "Zoom In Left" ], [ "zoom-in-right", "Zoom In Right" ], [ "zoom-out", "Zoom Out" ], [ "zoom-out-up", "Zoom Out Up" ], [ "zoom-out-down", "Zoom Out Down" ], [ "zoom-out-left", "Zoom Out Left" ], [ "zoom-out-right", "Zoom Out Right" ] ],
      "multiple" : false,
      "reordering_enabled" : true,
      "preset" : null,
      "type" : "choice",
      "display_width" : null,
      "default" : "default"
    }, {
      "id" : "animation.form.delay",
      "name" : "delay",
      "label" : "Delay",
      "help_text" : "Values from 0 to 3000, with step 50ms",
      "inline_help_text" : "Leave blank for default value from theme settings.",
      "required" : false,
      "locked" : false,
      "visibility" : {
        "controlling_field" : "is_aos",
        "controlling_field_path" : null,
        "controlling_value_regex" : "true",
        "property" : null,
        "operator" : "EQUAL",
        "access" : null
      },
      "display" : "text",
      "min" : 0,
      "max" : 3000,
      "step" : 50,
      "type" : "number",
      "display_width" : null
    } ],
    "tab" : "CONTENT",
    "expanded" : false,
    "group_occurrence_meta" : null,
    "type" : "group",
    "display_width" : null
  } ],
  "tab" : "CONTENT",
  "expanded" : false,
  "group_occurrence_meta" : null,
  "type" : "group",
  "display_width" : null
}, {
  "id" : "f19f3fe7-142c-d6b0-f4e9-bdd5eb82fe8e",
  "name" : "anchor_link_id",
  "label" : "Anchor Link ID",
  "help_text" : "Anchor Link ID to Jump to a Specific Part of a Page https://www.yoursite.com/this-page#anchor-link-id. The ID must begin with a letter ([A-Za-z]) and may be followed by any number of letters, digits ([0-9]), hyphens (\"-\"), underscores (\"_\"), colons (\":\"), and periods (\".\")",
  "required" : false,
  "locked" : false,
  "validation_regex" : "^[A-Za-z]+[\\w\\-\\:\\.]*$",
  "allow_new_line" : false,
  "type" : "text",
  "display_width" : null
} ]